django_admin_fast_search/__init__.py
django_admin_fast_search/admin.py
django_admin_fast_search/apps.py
django_admin_fast_search/models.py
django_admin_fast_search/urls.py
django_admin_fast_search/views.py
django_admin_fast_search/static/css/django_admin_fast_search.css
django_admin_fast_search/static/js/django_admin_fast_search.js
django_admin_fast_search/templates/admin/custom_boolean_filter_field.html
django_admin_fast_search/templates/admin/custom_change_list.html
django_admin_fast_search/templates/admin/custom_choice_filter_field.html
django_admin_fast_search/templates/admin/custom_date_filter_field.html
django_admin_fast_search/templates/admin/custom_model_choice_filter_field.html
django_admin_fast_search/templates/admin/custom_multiselect_filter_field.html
django_admin_fast_search/templates/admin/custom_number_filter_field.html
django_admin_fast_search/templates/admin/custom_search_field.html
django_admin_fast_search/templates/django_admin_fast_search/base.html
django_admin_fast_search-0.2.4.dist-info/AUTHORS.rst
django_admin_fast_search-0.2.4.dist-info/LICENSE
django_admin_fast_search-0.2.4.dist-info/METADATA
django_admin_fast_search-0.2.4.dist-info/WHEEL
django_admin_fast_search-0.2.4.dist-info/top_level.txt
django_admin_fast_search-0.2.4.dist-info/RECORD
